tm1filetools/__init__.py
tm1filetools/files/__init__.py
tm1filetools/files/base.py
tm1filetools/files/binary/__init__.py
tm1filetools/files/binary/binary.py
tm1filetools/files/binary/cube.py
tm1filetools/files/binary/dimension.py
tm1filetools/files/binary/feeders.py
tm1filetools/files/text/__init__.py
tm1filetools/files/text/blb.py
tm1filetools/files/text/cfg.py
tm1filetools/files/text/chore.py
tm1filetools/files/text/cma.py
tm1filetools/files/text/log.py
tm1filetools/files/text/other.py
tm1filetools/files/text/process.py
tm1filetools/files/text/rules.py
tm1filetools/files/text/subset.py
tm1filetools/files/text/text.py
tm1filetools/files/text/user_owned.py
tm1filetools/files/text/view.py
tm1filetools/tools/__init__.py
tm1filetools/tools/filetool.py
tm1filetools-0.3.3.dist-info/LICENSE
tm1filetools-0.3.3.dist-info/WHEEL
tm1filetools-0.3.3.dist-info/METADATA
tm1filetools-0.3.3.dist-info/RECORD
