Metadata-Version: 2.1
Name: tm1filetools
Version: 0.3.3
Summary: A package for working with files created by a TM1 database.
Author-email: Alexander Sutcliffe <sutcliffe.alex@gmail.com>
Requires-Python: >=3.9
Classifier: Programming Language :: Python :: 3
Classifier: License :: OSI Approved :: MIT License
Classifier: Operating System :: OS Independent
Classifier: Intended Audience :: Developers
Requires-Dist: chardet>=5.0.0
Project-URL: Bug Tracker, https://github.com/scrambldchannel/tm1-file-tools
Project-URL: Homepage, https://github.com/scrambldchannel/tm1-file-tools
